{"tara":{"@attributes":{"nume":"Romania"},"localitate":[{"@attributes":{"nume":"Arad"},"DataPrognozei":"2025-01-24","prognoza":[{"@attributes":{"data":"2025-01-25"},"temp_min":"-1","temp_max":"7","comment":{},"fenomen_descriere":"CER TEMPORAR NOROS, CEATA","fenomen_simbol":"008"},{"@attributes":{"data":"2025-01-26"},"temp_min":"-1","temp_max":"13","comment":{},"fenomen_descriere":"CER PARTIAL NOROS","fenomen_simbol":"001-2"},{"@attributes":{"data":"2025-01-27"},"temp_min":"2","temp_max":"15","comment":{},"fenomen_descriere":"CER VARIABIL","fenomen_simbol":"001"},{"@attributes":{"data":"2025-01-28"},"temp_min":"4","temp_max":"17","comment":{},"fenomen_descriere":"CER PARTIAL NOROS","fenomen_simbol":"001-2"},{"@attributes":{"data":"2025-01-29"},"temp_min":"6","temp_max":"15","comment":{},"fenomen_descriere":"CER MAI MULT NOROS, PLOAIE SLABA","fenomen_simbol":"202-2"}]},{"@attributes":{"nume":"Botosani"},"DataPrognozei":"2025-01-24","prognoza":[{"@attributes":{"data":"2025-01-25"},"temp_min":"1","temp_max":"8","comment":{},"fenomen_descriere":"CER PARTIAL NOROS","fenomen_simbol":"001-2"},{"@attributes":{"data":"2025-01-26"},"temp_min":"0","temp_max":"9","comment":{},"fenomen_descriere":"CER PARTIAL NOROS","fenomen_simbol":"001-2"},{"@attributes":{"data":"2025-01-27"},"temp_min":"1","temp_max":"13","comment":{},"fenomen_descriere":"CER PARTIAL NOROS","fenomen_simbol":"001-2"},{"@attributes":{"data":"2025-01-28"},"temp_min":"1","temp_max":"14","comment":{},"fenomen_descriere":"CER PARTIAL NOROS","fenomen_simbol":"001-2"},{"@attributes":{"data":"2025-01-29"},"temp_min":"2","temp_max":"11","comment":{},"fenomen_descriere":"CER MAI MULT NOROS, PLOAIE SLABA","fenomen_simbol":"202-2"}]},{"@attributes":{"nume":"Bucuresti"},"DataPrognozei":"2025-01-24","prognoza":[{"@attributes":{"data":"2025-01-25"},"temp_min":"4","temp_max":"11","comment":{},"fenomen_descriere":"CER VARIABIL","fenomen_simbol":"001"},{"@attributes":{"data":"2025-01-26"},"temp_min":"1","temp_max":"12","comment":{},"fenomen_descriere":"CER PARTIAL NOROS","fenomen_simbol":"001-2"},{"@attributes":{"data":"2025-01-27"},"temp_min":"2","temp_max":"14","comment":{},"fenomen_descriere":"CER VARIABIL","fenomen_simbol":"001"},{"@attributes":{"data":"2025-01-28"},"temp_min":"2","temp_max":"16","comment":{},"fenomen_descriere":"CER VARIABIL","fenomen_simbol":"001"},{"@attributes":{"data":"2025-01-29"},"temp_min":"2","temp_max":"16","comment":{},"fenomen_descriere":"CER VARIABIL","fenomen_simbol":"001"}]},{"@attributes":{"nume":"Cluj-Napoca"},"DataPrognozei":"2025-01-24","prognoza":[{"@attributes":{"data":"2025-01-25"},"temp_min":"-3","temp_max":"2","comment":{},"fenomen_descriere":"CER TEMPORAR NOROS, CEATA","fenomen_simbol":"008"},{"@attributes":{"data":"2025-01-26"},"temp_min":"-2","temp_max":"6","comment":{},"fenomen_descriere":"CER PARTIAL NOROS","fenomen_simbol":"001-2"},{"@attributes":{"data":"2025-01-27"},"temp_min":"1","temp_max":"8","comment":{},"fenomen_descriere":"CER PARTIAL NOROS","fenomen_simbol":"001-2"},{"@attributes":{"data":"2025-01-28"},"temp_min":"-1","temp_max":"13","comment":{},"fenomen_descriere":"CER PARTIAL NOROS","fenomen_simbol":"001-2"},{"@attributes":{"data":"2025-01-29"},"temp_min":"3","temp_max":"12","comment":{},"fenomen_descriere":"CER PARTIAL NOROS","fenomen_simbol":"001-2"}]},{"@attributes":{"nume":"Constanta"},"DataPrognozei":"2025-01-24","prognoza":[{"@attributes":{"data":"2025-01-25"},"temp_min":"6","temp_max":"8","comment":{},"fenomen_descriere":"CER MAI MULT NOROS, PLOAIE SLABA","fenomen_simbol":"202-2"},{"@attributes":{"data":"2025-01-26"},"temp_min":"6","temp_max":"10","comment":{},"fenomen_descriere":"CER PARTIAL NOROS","fenomen_simbol":"001-2"},{"@attributes":{"data":"2025-01-27"},"temp_min":"6","temp_max":"12","comment":{},"fenomen_descriere":"CER VARIABIL","fenomen_simbol":"001"},{"@attributes":{"data":"2025-01-28"},"temp_min":"4","temp_max":"12","comment":{},"fenomen_descriere":"CER VARIABIL","fenomen_simbol":"001"},{"@attributes":{"data":"2025-01-29"},"temp_min":"6","temp_max":"14","comment":{},"fenomen_descriere":"CER VARIABIL","fenomen_simbol":"001"}]},{"@attributes":{"nume":"Craiova"},"DataPrognozei":"2025-01-24","prognoza":[{"@attributes":{"data":"2025-01-25"},"temp_min":"1","temp_max":"11","comment":{},"fenomen_descriere":"CER VARIABIL","fenomen_simbol":"001"},{"@attributes":{"data":"2025-01-26"},"temp_min":"0","temp_max":"10","comment":{},"fenomen_descriere":"CER PARTIAL NOROS","fenomen_simbol":"001-2"},{"@attributes":{"data":"2025-01-27"},"temp_min":"0","temp_max":"13","comment":{},"fenomen_descriere":"CER VARIABIL","fenomen_simbol":"001"},{"@attributes":{"data":"2025-01-28"},"temp_min":"1","temp_max":"13","comment":{},"fenomen_descriere":"CER VARIABIL","fenomen_simbol":"001"},{"@attributes":{"data":"2025-01-29"},"temp_min":"2","temp_max":"13","comment":{},"fenomen_descriere":"CER PARTIAL NOROS","fenomen_simbol":"001-2"}]},{"@attributes":{"nume":"Iasi"},"DataPrognozei":"2025-01-24","prognoza":[{"@attributes":{"data":"2025-01-25"},"temp_min":"2","temp_max":"8","comment":{},"fenomen_descriere":"CER PARTIAL NOROS","fenomen_simbol":"001-2"},{"@attributes":{"data":"2025-01-26"},"temp_min":"2","temp_max":"11","comment":{},"fenomen_descriere":"CER PARTIAL NOROS","fenomen_simbol":"001-2"},{"@attributes":{"data":"2025-01-27"},"temp_min":"3","temp_max":"12","comment":{},"fenomen_descriere":"CER PARTIAL NOROS","fenomen_simbol":"001-2"},{"@attributes":{"data":"2025-01-28"},"temp_min":"1","temp_max":"12","comment":{},"fenomen_descriere":"CER PARTIAL NOROS","fenomen_simbol":"001-2"},{"@attributes":{"data":"2025-01-29"},"temp_min":"3","temp_max":"12","comment":{},"fenomen_descriere":"CER PARTIAL NOROS","fenomen_simbol":"001-2"}]},{"@attributes":{"nume":"Rm. Valcea"},"DataPrognozei":"2025-01-24","prognoza":[{"@attributes":{"data":"2025-01-25"},"temp_min":"0","temp_max":"12","comment":{},"fenomen_descriere":"CER VARIABIL","fenomen_simbol":"001"},{"@attributes":{"data":"2025-01-26"},"temp_min":"-1","temp_max":"12","comment":{},"fenomen_descriere":"CER PARTIAL NOROS","fenomen_simbol":"001-2"},{"@attributes":{"data":"2025-01-27"},"temp_min":"0","temp_max":"15","comment":{},"fenomen_descriere":"CER VARIABIL","fenomen_simbol":"001"},{"@attributes":{"data":"2025-01-28"},"temp_min":"1","temp_max":"18","comment":{},"fenomen_descriere":"CER VARIABIL","fenomen_simbol":"001"},{"@attributes":{"data":"2025-01-29"},"temp_min":"2","temp_max":"16","comment":{},"fenomen_descriere":"CER VARIABIL","fenomen_simbol":"001"}]},{"@attributes":{"nume":"Sibiu"},"DataPrognozei":"2025-01-24","prognoza":[{"@attributes":{"data":"2025-01-25"},"temp_min":"-2","temp_max":"8","comment":{},"fenomen_descriere":"CER PARTIAL NOROS","fenomen_simbol":"001-2"},{"@attributes":{"data":"2025-01-26"},"temp_min":"-3","temp_max":"12","comment":{},"fenomen_descriere":"CER VARIABIL","fenomen_simbol":"001"},{"@attributes":{"data":"2025-01-27"},"temp_min":"-1","temp_max":"13","comment":{},"fenomen_descriere":"CER VARIABIL","fenomen_simbol":"001"},{"@attributes":{"data":"2025-01-28"},"temp_min":"-2","temp_max":"15","comment":{},"fenomen_descriere":"CER VARIABIL","fenomen_simbol":"001"},{"@attributes":{"data":"2025-01-29"},"temp_min":"1","temp_max":"14","comment":{},"fenomen_descriere":"CER VARIABIL","fenomen_simbol":"001"}]},{"@attributes":{"nume":"Sulina"},"DataPrognozei":"2025-01-24","prognoza":[{"@attributes":{"data":"2025-01-25"},"temp_min":"6","temp_max":"8","comment":{},"fenomen_descriere":"CER MAI MULT NOROS, PLOAIE SLABA","fenomen_simbol":"202-2"},{"@attributes":{"data":"2025-01-26"},"temp_min":"6","temp_max":"10","comment":{},"fenomen_descriere":"CER PARTIAL NOROS","fenomen_simbol":"001-2"},{"@attributes":{"data":"2025-01-27"},"temp_min":"7","temp_max":"10","comment":{},"fenomen_descriere":"CER VARIABIL","fenomen_simbol":"001"},{"@attributes":{"data":"2025-01-28"},"temp_min":"6","temp_max":"10","comment":{},"fenomen_descriere":"CER VARIABIL","fenomen_simbol":"001"},{"@attributes":{"data":"2025-01-29"},"temp_min":"7","temp_max":"11","comment":{},"fenomen_descriere":"CER VARIABIL","fenomen_simbol":"001"}]}]}}